CHANGES.txt
COPYRIGHT.txt
LICENSE.txt
README.txt
ez_setup.py
setup.cfg
setup.py
repoze/__init__.py
repoze.bfg.traversalwrapper.egg-info/PKG-INFO
repoze.bfg.traversalwrapper.egg-info/SOURCES.txt
repoze.bfg.traversalwrapper.egg-info/dependency_links.txt
repoze.bfg.traversalwrapper.egg-info/entry_points.txt
repoze.bfg.traversalwrapper.egg-info/namespace_packages.txt
repoze.bfg.traversalwrapper.egg-info/not-zip-safe
repoze.bfg.traversalwrapper.egg-info/requires.txt
repoze.bfg.traversalwrapper.egg-info/top_level.txt
repoze/bfg/__init__.py
repoze/bfg/traversalwrapper/__init__.py
repoze/bfg/traversalwrapper/tests.py