Metadata-Version: 1.0
Name: repoze.bfg.traversalwrapper
Version: 0.3
Summary: An add-on for the repoze.bfg web framework which supplies a model graph traverser which proxies location-ignorant model objects
Home-page: http://bfg.repoze.org
Author: Agendaless Consulting
Author-email: repoze-dev@lists.repoze.org
License: BSD-derived (http://www.repoze.org/LICENSE.txt)
Keywords: bfg repoze.bfg traverser traversal proxy
Platform: UNKNOWN
Classifier: Intended Audience :: Developers
Classifier: Programming Language :: Python
